odoo/addons/ssi_production_lot_qrcode/README.rst
odoo/addons/ssi_production_lot_qrcode/__init__.py
odoo/addons/ssi_production_lot_qrcode/__manifest__.py
odoo/addons/ssi_production_lot_qrcode/models/__init__.py
odoo/addons/ssi_production_lot_qrcode/models/stock_production_lot.py
odoo/addons/ssi_production_lot_qrcode/static/description/icon.png
odoo14_addon_ssi_production_lot_qrcode-14.0.1.0.0.dist-info/METADATA
odoo14_addon_ssi_production_lot_qrcode-14.0.1.0.0.dist-info/WHEEL
odoo14_addon_ssi_production_lot_qrcode-14.0.1.0.0.dist-info/top_level.txt
odoo14_addon_ssi_production_lot_qrcode-14.0.1.0.0.dist-info/RECORD
